capiche/__init__.py
capiche/examples/__init__.py
capiche/examples/basic.py
capiche/lib/__init__.py
capiche/lib/constants.py
capiche/lib/exceptions.py
capiche-0.0.6.dist-info/LICENSE
capiche-0.0.6.dist-info/METADATA
capiche-0.0.6.dist-info/WHEEL
capiche-0.0.6.dist-info/top_level.txt
capiche-0.0.6.dist-info/RECORD
